fsm-assignments/problem4_link/slave_fsm.v
module slave_fsm(
    input  wire       clk,
    input  wire       rst, 
    input  wire       req,
    input  wire [7:0] data_in,
    output wire       ack,
    output wire [7:0] last_byte
);

reg ack_r;
reg [7:0] last_byte_r;
reg [1:0] ack_cnt;
reg [1:0] state;

assign ack = ack_r;
assign last_byte = last_byte_r;

localparam WAITREQ = 2'd0;
localparam ASSERT1 = 2'd1; // first ack cycle
localparam ASSERT2 = 2'd2; // second ack cycle
localparam WAITDROP = 2'd3; // wait for req to drop, then release ack

always @(posedge clk) begin
    if (rst) begin
        ack_r <= 1'b0;
        last_byte_r <= 8'd0;
        ack_cnt <= 2'd0;
        state <= WAITREQ;
    end else begin
        case (state)
            WAITREQ: begin
                ack_r <= 1'b0;
                ack_cnt <= 2'd0;
                if (req) begin
                    // latch data on request
                    last_byte_r <= data_in;
                    // start asserting ack for two cycles
                    ack_r <= 1'b1;
                    ack_cnt <= 2'd1;
                    state <= ASSERT2;
                end
            end

            ASSERT2: begin
                // second cycle of ack
                ack_r <= 1'b1;
                ack_cnt <= 2'd2;
                state <= WAITDROP;
            end

            WAITDROP: begin
                // ack remains 1 while waiting for master to drop req
                ack_r <= 1'b1;
                if (!req) begin
                    // master dropped req -> release ack next cycle
                    ack_r <= 1'b0;
                    ack_cnt <= 2'd0;
                    state <= WAITREQ;
                end
            end

            default: state <= WAITREQ;
        endcase
    end
end

endmodule

fsm-assignments/problem4_link/master_fsm.v
module master_fsm(
    input  wire       clk,
    input  wire       rst, 
    input  wire       ack,
    output wire       req,
    output wire [7:0] data,
    output wire       done 
);

reg req_r;
reg [7:0] data_r;
reg done_r;
reg [1:0] byte_idx;
reg [2:0] state;

assign req  = req_r;
assign data = data_r;
assign done = done_r;

localparam S_REQ        = 3'd0;
localparam S_WAIT_ACK_DROP = 3'd1;
localparam S_DONE       = 3'd2;
localparam S_IDLE       = 3'd3;

always @(posedge clk) begin
    if (rst) begin
        req_r   <= 1'b0;
        data_r  <= 8'hA0; 
        done_r  <= 1'b0;
        byte_idx<= 2'd0;
        state   <= S_REQ; 
    end else begin
        // default
        done_r <= 1'b0;

        case (state)
            S_REQ: begin
                req_r <= 1'b1;
                data_r<= 8'hA0 + byte_idx;
                if (ack) begin
                    state <= S_WAIT_ACK_DROP;
                end
            end

            S_WAIT_ACK_DROP: begin
                req_r <= 1'b0;
                if (!ack) begin
                    if (byte_idx == 2'd3) begin
                        state <= S_DONE;
                    end else begin
                        byte_idx <= byte_idx + 1'b1;
                        state <= S_REQ;
                    end
                end
            end

            S_DONE: begin
                done_r <= 1'b1; 
                state <= S_IDLE;
            end

            S_IDLE: begin
                req_r <= 1'b0;
            end

            default: state <= S_REQ;
        endcase
    end
end

endmodule

fsm-assignments/problem4_link/link_top.v
module link_top(
    input  wire clk,
    input  wire rst,
    output wire done
);

wire req;
wire ack;
wire [7:0] data;
wire [7:0] last_byte;

master_fsm master_inst(
    .clk(clk),
    .rst(rst),
    .ack(ack),
    .req(req),
    .data(data),
    .done(done)
);

slave_fsm slave_inst(
    .clk(clk),
    .rst(rst),
    .req(req),
    .data_in(data),
    .ack(ack),
    .last_byte(last_byte)
);

endmodule

fsm-assignments/problem4_link/tb_link_top.v
`timescale 1ns/1ps
module tb_link_top;

reg clk;
reg rst;
wire done;

link_top dut(.clk(clk), .rst(rst), .done(done));

initial begin
    $dumpfile("dump.vcd");
    $dumpvars(0, tb_link_top);
end

initial begin
    clk = 0;
    forever #5 clk = ~clk;
end

initial begin
    rst = 1;
    #20;
    rst = 0;

    $display("TIME  REQ ACK DATA LAST_BYTE DONE");
    $monitor("%0t  %b   %b  %02h   %02h       %b", $time,
             dut.master_inst.req,
             dut.slave_inst.ack,
             dut.master_inst.data,
             dut.slave_inst.last_byte,
             dut.done);

   
    wait (done == 1);
    #20;
    $display("Burst complete at time %0t", $time);
    $finish;
end

endmodule

fsm-assignments/problem4_link/dump.vcd
$date
	Tue Aug 19 03:48:40 2025
$end
$version
	Icarus Verilog
$end
$timescale
	1ps
$end
$scope module tb_link_top $end
$var wire 1 ! done $end
$var reg 1 " clk $end
$var reg 1 # rst $end
$scope module dut $end
$var wire 1 " clk $end
$var wire 1 # rst $end
$var wire 1 $ req $end
$var wire 8 % last_byte [7:0] $end
$var wire 1 ! done $end
$var wire 8 & data [7:0] $end
$var wire 1 ' ack $end
$scope module master_inst $end
$var wire 1 " clk $end
$var wire 8 ( data [7:0] $end
$var wire 1 ! done $end
$var wire 1 $ req $end
$var wire 1 # rst $end
$var wire 1 ' ack $end
$var parameter 3 ) S_DONE $end
$var parameter 3 * S_IDLE $end
$var parameter 3 + S_REQ $end
$var parameter 3 , S_WAIT_ACK_DROP $end
$var reg 2 - byte_idx [1:0] $end
$var reg 8 . data_r [7:0] $end
$var reg 1 / done_r $end
$var reg 1 0 req_r $end
$var reg 3 1 state [2:0] $end
$upscope $end
$scope module slave_inst $end
$var wire 1 ' ack $end
$var wire 1 " clk $end
$var wire 8 2 data_in [7:0] $end
$var wire 8 3 last_byte [7:0] $end
$var wire 1 $ req $end
$var wire 1 # rst $end
$var parameter 2 4 ASSERT1 $end
$var parameter 2 5 ASSERT2 $end
$var parameter 2 6 WAITDROP $end
$var parameter 2 7 WAITREQ $end
$var reg 2 8 ack_cnt [1:0] $end
$var reg 1 9 ack_r $end
$var reg 8 : last_byte_r [7:0] $end
$var reg 2 ; state [1:0] $end
$upscope $end
$upscope $end
$upscope $end
$enddefinitions $end
$comment Show the parameter values. $end
$dumpall
b0 7
b11 6
b10 5
b1 4
b1 ,
b0 +
b11 *
b10 )
$end
#0
$dumpvars
bx ;
bx :
x9
bx 8
bx 3
bx 2
bx 1
x0
x/
bx .
bx -
bx (
x'
bx &
bx %
x$
1#
0"
x!
$end
#5000
b0 1
b0 -
0!
0/
b10100000 &
b10100000 (
b10100000 2
b10100000 .
0$
00
b0 ;
b0 8
b0 %
b0 3
b0 :
0'
09
1"
#10000
0"
#15000
1"
#20000
0"
0#
#25000
1$
10
1"
#30000
0"
#35000
b10 ;
b1 8
1'
19
b10100000 %
b10100000 3
b10100000 :
1"
#40000
0"
#45000
b1 1
b11 ;
b10 8
1"
#50000
0"
#55000
0$
00
1"
#60000
0"
#65000
b0 ;
b0 8
0'
09
1"
#70000
0"
#75000
b0 1
b1 -
1"
#80000
0"
#85000
b10100001 &
b10100001 (
b10100001 2
b10100001 .
1$
10
1"
#90000
0"
#95000
b10 ;
b1 8
1'
19
b10100001 %
b10100001 3
b10100001 :
1"
#100000
0"
#105000
b1 1
b11 ;
b10 8
1"
#110000
0"
#115000
0$
00
1"
#120000
0"
#125000
b0 ;
b0 8
0'
09
1"
#130000
0"
#135000
b0 1
b10 -
1"
#140000
0"
#145000
b10100010 &
b10100010 (
b10100010 2
b10100010 .
1$
10
1"
#150000
0"
#155000
b10 ;
b1 8
1'
19
b10100010 %
b10100010 3
b10100010 :
1"
#160000
0"
#165000
b1 1
b11 ;
b10 8
1"
#170000
0"
#175000
0$
00
1"
#180000
0"
#185000
b0 ;
b0 8
0'
09
1"
#190000
0"
#195000
b0 1
b11 -
1"
#200000
0"
#205000
b10100011 &
b10100011 (
b10100011 2
b10100011 .
1$
10
1"
#210000
0"
#215000
b10 ;
b1 8
1'
19
b10100011 %
b10100011 3
b10100011 :
1"
#220000
0"
#225000
b1 1
b11 ;
b10 8
1"
#230000
0"
#235000
0$
00
1"
#240000
0"
#245000
b0 ;
b0 8
0'
09
1"
#250000
0"
#255000
b10 1
1"
#260000
0"
#265000
b11 1
1!
1/
1"
#270000
0"
#275000
0!
0/
1"
