fsm-assignments/problem3_vending/vending_mealy.v
module vending_mealy(
    input  wire       clk,
    input  wire       rst,  
    input  wire [1:0] coin,  // 01=5, 10=10, 00=idle 
    output wire       dispense, 
    output wire       chg5     
);

localparam [1:0] S0  = 2'd0;
localparam [1:0] S5  = 2'd1;
localparam [1:0] S10 = 2'd2;
localparam [1:0] S15 = 2'd3;

reg [1:0] state, next_state;
reg dispense_r, chg5_r;

assign dispense = dispense_r;
assign chg5    = chg5_r;

always @(*) begin
   
    next_state  = state;
    dispense_r  = 1'b0;
    chg5_r      = 1'b0;

    case (state)
        S0: begin
            case (coin)
                2'b01: next_state = S5;   // +5
                2'b10: next_state = S10;  // +10
                default: next_state = S0;
            endcase
        end
        S5: begin
            case (coin)
                2'b01: next_state = S10;  // 5+5 = 10
                2'b10: next_state = S15;  // 5+10 = 15
                default: next_state = S5;
            endcase
        end
        S10: begin
            case (coin)
                2'b01: next_state = S15;  // 10+5 = 15
                2'b10: begin              // 10+10 = 20 -> vend
                    next_state  = S0;     // reset total after vend
                    dispense_r  = 1'b1;
                    chg5_r      = 1'b0;
                end
                default: next_state = S10;
            endcase
        end
        S15: begin
            case (coin)
                2'b01: begin              // 15+5 = 20 -> vend
                    next_state  = S0;
                    dispense_r  = 1'b1;
                    chg5_r      = 1'b0;
                end
                2'b10: begin              // 15+10 = 25 -> vend + change(5)
                    next_state  = S0;
                    dispense_r  = 1'b1;
                    chg5_r      = 1'b1;
                end
                default: next_state = S15;
            endcase
        end
        default: begin
            next_state = S0;
        end
    endcase
end

// Synchronous state register with synchronous active-high reset
always @(posedge clk) begin
    if (rst) begin
        state <= S0;
    end else begin
        state <= next_state;
    end
end

endmodule

fsm-assignments/problem3_vending/tb_vending_mealy.v
`timescale 1ns/1ps
module tb_vending_mealy;

reg clk, rst;
reg [1:0] coin;
wire dispense, chg5;

vending_mealy dut(
    .clk(clk),
    .rst(rst),
    .coin(coin),
    .dispense(dispense),
    .chg5(chg5)
);

initial begin
    clk = 0;
    forever #5 clk = ~clk;
end

initial begin
    $dumpfile("dump.vcd");
    $dumpvars(0, tb_vending_mealy);
end


task put5;
begin
    coin = 2'b01;
    @(posedge clk); 
    coin = 2'b00;
    #1; 
end
endtask

task put10;
begin
    coin = 2'b10;
    @(posedge clk);
    coin = 2'b00;
    #1;
end
endtask

always @(posedge clk) begin
    $display("%0t : coin=%b state=%0d dispense=%b chg5=%b",
        $time, coin, dut.state, dispense, chg5);
end

// Test sequence
initial begin
    
    coin = 2'b00;
    rst  = 1'b1;
    repeat (2) @(posedge clk); // apply synchronous reset for 2 posedges
    rst = 1'b0;

    put10;      
    put5;          
    put5;           
    put10;          
    put10;     
    put5;     
    put10;      
    put10; 

    repeat (2) @(posedge clk);
    $display("Test complete");
    $finish;
end

endmodule

fsm-assignments/problem3_vending/dump.vcd
$date
	Tue Aug 19 03:38:48 2025
$end
$version
	Icarus Verilog
$end
$timescale
	1ps
$end
$scope module tb_vending_mealy $end
$var wire 1 ! dispense $end
$var wire 1 " chg5 $end
$var reg 1 # clk $end
$var reg 2 $ coin [1:0] $end
$var reg 1 % rst $end
$scope module dut $end
$var wire 1 " chg5 $end
$var wire 1 # clk $end
$var wire 2 & coin [1:0] $end
$var wire 1 ! dispense $end
$var wire 1 % rst $end
$var parameter 2 ' S0 $end
$var parameter 2 ( S10 $end
$var parameter 2 ) S15 $end
$var parameter 2 * S5 $end
$var reg 1 + chg5_r $end
$var reg 1 , dispense_r $end
$var reg 2 - next_state [1:0] $end
$var reg 2 . state [1:0] $end
$upscope $end
$scope task put10 $end
$upscope $end
$scope task put5 $end
$upscope $end
$upscope $end
$enddefinitions $end
$comment Show the parameter values. $end
$dumpall
b1 *
b11 )
b10 (
b0 '
$end
#0
$dumpvars
bx .
b0 -
0,
0+
b0 &
1%
b0 $
0#
0"
0!
$end
#5000
b0 .
1#
#10000
0#
#15000
b10 -
b10 $
b10 &
0%
1#
#20000
0#
#25000
b10 .
b10 -
b0 $
b0 &
1#
#26000
b11 -
b1 $
b1 &
#30000
0#
#35000
b11 .
b11 -
b0 $
b0 &
1#
#36000
1!
1,
b0 -
b1 $
b1 &
#40000
0#
#45000
b0 .
0!
0,
b0 -
b0 $
b0 &
1#
#46000
b10 -
b10 $
b10 &
#50000
0#
#55000
b10 .
b10 -
b0 $
b0 &
1#
#56000
1!
1,
b0 -
b10 $
b10 &
#60000
0#
#65000
b0 .
0!
0,
b0 -
b0 $
b0 &
1#
#66000
b1 -
b1 $
b1 &
#70000
0#
#75000
b1 .
b1 -
b0 $
b0 &
1#
#76000
b11 -
b10 $
b10 &
#80000
0#
#85000
b11 .
b11 -
b0 $
b0 &
1#
#86000
1"
1+
1!
1,
b0 -
b10 $
b10 &
#90000
0#
#95000
b0 .
0"
0+
0!
0,
b0 -
b0 $
b0 &
1#
