fsm-assignments/problem1_seqdet/seq_detect_mealy.v
module seq_detect_mealy(
    input  wire clk,
    input  wire rst, 
    input  wire din,
    output wire y  
);

    // State encoding
    localparam S0 = 2'b00;
    localparam S1 = 2'b01;
    localparam S2 = 2'b10;
    localparam S3 = 2'b11;

    reg [1:0] state, next_state;
    reg       y_reg;

    // Combinational next-state + Mealy output logic
    always @(*) begin
        
        next_state = state;
        y_reg = 1'b0;

        case (state)
            S0: begin
                if (din) next_state = S1;
                else     next_state = S0;
            end
            S1: begin
                if (din) next_state = S2;
                else     next_state = S0;
            end
            S2: begin
                if (din) begin
                    next_state = S2;
                end else begin
                    next_state = S3;
                end
            end
            S3: begin
                if (din) begin
                    y_reg = 1'b1;   
                    next_state = S1;
                end else begin
                    next_state = S0;
                end
            end
            default: begin
                next_state = S0;
                y_reg = 1'b0;
            end
        endcase
    end

    always @(posedge clk) begin
        if (rst) begin
            state <= S0;
        end else begin
            state <= next_state;
        end
    end

    assign y = y_reg;

endmodule

fsm-assignments/problem1_seqdet/tb_seq_detect_mealy.v
`timescale 1ns/1ps
module tb_seq_detect_mealy;
    reg clk, rst, din;
    wire y;
    integer i;
    integer cycle;

    reg [10:0] stream;

    seq_detect_mealy uut (
        .clk(clk),
        .rst(rst),
        .din(din),
        .y(y)
    );

    initial begin
        clk = 0;
        forever #5 clk = ~clk;
    end

    // Cycle counter
    always @(posedge clk) cycle = cycle + 1;

    initial begin
        $dumpfile("dump.vcd");
        $dumpvars(0, tb_seq_detect_mealy);

        
        cycle = 0;
        din = 0;
        rst = 1;
       
        repeat (3) @(posedge clk);
       
        @(posedge clk);
        rst = 0;
        @(posedge clk);

        stream = 11'b11011011101;

        $display("Cycle din y   (bit_idx 0-based into stream)");
       
        for (i = 0; i < 11; i = i + 1) begin
            @(posedge clk);
            din = stream[10 - i];
            #1; // let combinational y settle
            $display("%4d   %b   %b", i, din, y);
        end

        // stop after some cycles
        @(posedge clk); din = 0;
        @(posedge clk);
        $finish;
    end
endmodule

fsm-assignments/problem1_seqdet/dump.vcd
$date
	Tue Aug 19 03:09:03 2025
$end
$version
	Icarus Verilog
$end
$timescale
	1ps
$end
$scope module tb_seq_detect_mealy $end
$var wire 1 ! y $end
$var reg 1 " clk $end
$var reg 1 # din $end
$var reg 1 $ rst $end
$var reg 11 % stream [10:0] $end
$var integer 32 & cycle [31:0] $end
$var integer 32 ' i [31:0] $end
$scope module uut $end
$var wire 1 " clk $end
$var wire 1 # din $end
$var wire 1 $ rst $end
$var wire 1 ! y $end
$var parameter 2 ( S0 $end
$var parameter 2 ) S1 $end
$var parameter 2 * S2 $end
$var parameter 2 + S3 $end
$var reg 2 , next_state [1:0] $end
$var reg 2 - state [1:0] $end
$var reg 1 . y_reg $end
$upscope $end
$upscope $end
$enddefinitions $end
$comment Show the parameter values. $end
$dumpall
b11 +
b10 *
b1 )
b0 (
$end
#0
$dumpvars
0.
bx -
b0 ,
bx '
b0 &
bx %
1$
0#
0"
0!
$end
#5000
b0 -
b1 &
1"
#10000
0"
#15000
b10 &
1"
#20000
0"
#25000
b11 &
1"
#30000
0"
#35000
0$
b100 &
1"
#40000
0"
#45000
b101 &
b0 '
b11011011101 %
1"
#50000
0"
#55000
b1 ,
1#
b110 &
1"
#56000
b1 '
#60000
0"
#65000
b10 ,
b1 -
b111 &
1"
#66000
b10 '
#70000
0"
#75000
b10 -
b11 ,
b1000 &
0#
1"
#76000
b11 '
#80000
0"
#85000
1!
1.
b11 -
b1 ,
b1001 &
1#
1"
#86000
b100 '
#90000
0"
#95000
b10 ,
0!
0.
b1 -
b1010 &
1"
#96000
b101 '
#100000
0"
#105000
b10 -
b11 ,
b1011 &
0#
1"
#106000
b110 '
#110000
0"
#115000
1!
1.
b11 -
b1 ,
b1100 &
1#
1"
#116000
b111 '
#120000
0"
#125000
b10 ,
0!
0.
b1 -
b1101 &
1"
#126000
b1000 '
#130000
0"
#135000
b10 -
b1110 &
1"
#136000
b1001 '
#140000
0"
#145000
b11 ,
b1111 &
0#
1"
#146000
b1010 '
#150000
0"
#155000
1!
1.
b11 -
b1 ,
b10000 &
1#
1"
#156000
b1011 '
#160000
0"
#165000
b1 -
0!
0.
b0 ,
b10001 &
0#
1"
#170000
0"
#175000
b0 -
b10010 &
1"
